{"Entered": "Yes", "Exited": "Yes", "date_num": 12042022, "Strategy": "Straddle2", "Entry_Time": 94401, "CE_Symbol": "NSE:BANKNIFTY2241337400CE", "PE_Symbol": "NSE:BANKNIFTY2241337400PE", "CE_Entry_Price": 253.5, "PE_Entry_Price": 231.45, "CE_SL": 353.5, "PE_SL": 231.35, "CE_Exit_Price": 353.5, "PE_Exit_Price": 75.65, "CE_Exit_Time": 140513, "PE_Exit_Time": 150901, "CE_leg_ID": "", "PE_leg_ID": "", "CE_leg_SL_ID": "", "PE_leg_SL_ID": "", "Number_Of_Leg_In": 0, "CE_Price": 253.1, "PE_Price": 231.35}